wsgilog/__init__.py
wsgilog-0.3.1.dist-info/DESCRIPTION.rst
wsgilog-0.3.1.dist-info/METADATA
wsgilog-0.3.1.dist-info/RECORD
wsgilog-0.3.1.dist-info/WHEEL
wsgilog-0.3.1.dist-info/metadata.json
wsgilog-0.3.1.dist-info/top_level.txt
wsgilog-0.3.1.dist-info/zip-safe
