Metadata-Version: 2.0
Name: wsgilog
Version: 0.3.1
Summary: WSGI logging and event reporting middleware.
Home-page: UNKNOWN
Author: L. C. Rees
Author-email: lcrees@gmail.com
License: BSD
Keywords: WSGI logging middleware web http
Platform: UNKNOWN
Classifier: Development Status :: 4 - Beta
Classifier: Environment :: Web Environment
Classifier: License :: OSI Approved :: BSD License
Classifier: Natural Language :: English
Classifier: Operating System :: OS Independent
Classifier: Programming Language :: Python
Classifier: Topic :: System :: Monitoring
Classifier: Topic :: System :: Logging
Classifier: Topic :: Internet :: WWW/HTTP :: Site Management
Classifier: Topic :: Internet :: WWW/HTTP :: WSGI
Classifier: Topic :: Internet :: WWW/HTTP :: WSGI :: Middleware
